README.md
setup.cfg
setup.py
groupc_dct_risk/__init__.py
groupc_dct_risk.egg-info/PKG-INFO
groupc_dct_risk.egg-info/SOURCES.txt
groupc_dct_risk.egg-info/dependency_links.txt
groupc_dct_risk.egg-info/not-zip-safe
groupc_dct_risk.egg-info/top_level.txt