Metadata-Version: 1.0
Name: groupc-dct-risk
Version: 0.2
Summary: Group C Class: Risk-Based-Segementation when a custom would default or not.
Home-page: https://github.com/artadini/Risk-Based-Segementation
Author: Group C
Author-email: artadini@student.ie.edu
License: MIT
Platform: UNKNOWN
